{
  "MultiDiffusion": "MultiDiffusion",
  "Enable MultiDiffusion": "MultiDiffusionを有効にする",
  "Overwrite image size": "現在の画像サイズで上書き",
  "Keep input image size": "入力画像のサイズを維持する",
  "Image width": "画像の幅",
  "Image height": "画像の高さ：",
  "Latent tile width": "Latentタイルの幅",
  "Latent tile height": "Latentタイルの高さ",
  "Latent tile overlap": "Latentタイルの重なり幅",
  "Latent tile batch size": "Latentタイル バッチサイズ",
  "Move ControlNet images to CPU (if applicable)": "ControlNetの画像をCPUに移動 (可能な場合)",
  "Tiled VAE": "Tiled VAE",
  "Enable": "有効化",
  "Move VAE to GPU": "VAEをGPUに移動",
  "Please use smaller tile size when see CUDA error: out of memory.": "CUDA error: out of memoryが発生した場合は、タイルサイズを小さくしてください。",
  "Encoder Tile Size": "エンコーダタイルのサイズ",
  "Decoder Tile Size": "デコーダーのタイルサイズ",
  "Reset Tile Size": "タイルサイズをリセット。",
  "Fast Encoder": "高速エンコーダ",
  "Fast Decoder": "高速デコーダ",
  "Fast Encoder may change colors; Can fix it with more RAM and lower speed.": "高速エンコーダは色が変わる可能性があります。これはメモリを増やしたり低速にする事で改善できます。",
  "Encoder Color Fix": "高速エンコーダの色修正を使用",
  "multidiffusion-upscaler-for-automatic1111": "multidiffusion-upscaler-for-automatic1111",
  "https://github.com/pkuliyi2015/multidiffusion-upscaler-for-automatic1111.git": "https://github.com/pkuliyi2015/multidiffusion-upscaler-for-automatic1111.git"
}
