{
  "Seed travel": "crwdns45899:0crwdne45899:0",
  "Destination seed(s) (Comma separated)": "crwdns45901:0crwdne45901:0",
  "Only use Random seeds (Unless comparing paths)": "crwdns45903:0crwdne45903:0",
  "Number of random seed(s)": "crwdns45905:0crwdne45905:0",
  "Compare paths (Separate travels from 1st seed to each destination)": "crwdns45907:0crwdne45907:0",
  "Steps (Number of images between each seed)": "crwdns45909:0crwdne45909:0",
  "Loop back to initial seed": "crwdns45911:0crwdne45911:0",
  "Save results as video": "crwdns45913:0crwdne45913:0",
  "Frames per second": "crwdns45915:0crwdne45915:0",
  "Number of frames for lead in/out": "crwdns45917:0crwdne45917:0",
  "Upscale ratio": "crwdns45919:0crwdne45919:0",
  "Bump seed (If > 0 do a Compare Paths but only one image. No video will be generated.)": "crwdns45921:0crwdne45921:0",
  "Use cache": "crwdns45923:0crwdne45923:0",
  "Show generated images in ui": "crwdns45925:0crwdne45925:0",
  "Interpolation rate": "crwdns45927:0crwdne45927:0",
  "Linear": "crwdns45929:0crwdne45929:0",
  "Hug-the-middle": "crwdns45931:0crwdne45931:0",
  "Slow start": "crwdns45933:0crwdne45933:0",
  "Quick start": "crwdns45935:0crwdne45935:0",
  "Rate strength": "crwdns45937:0crwdne45937:0",
  "Allow the default Euler a Sampling method. (Does not produce good results)": "crwdns45939:0crwdne45939:0",
  "seed_travel": "crwdns45941:0crwdne45941:0",
  "https://github.com/yownas/seed_travel.git": "crwdns45943:0crwdne45943:0"
}
